UAutoml.py
UAutoml-0.0.4.dist-info/LICENSE.txt
UAutoml-0.0.4.dist-info/METADATA
UAutoml-0.0.4.dist-info/WHEEL
UAutoml-0.0.4.dist-info/top_level.txt
UAutoml-0.0.4.dist-info/RECORD
