Metadata-Version: 2.1
Name: UAutoml
Version: 0.0.4
Summary: Automated Machine Learning Framework for Data Analysis.
Home-page: https://github.com/ujjwalredd/Automated-Machine-Learning-Framework-for-Data-Analysis
Author: Ujjwal Reddy K S
License: UNKNOWN
Keywords: ML,Auto Data Analysis,models
Platform: UNKNOWN
Classifier: Programming Language :: Python :: 3
Classifier: License :: OSI Approved :: MIT License
Classifier: Operating System :: OS Independent
Requires-Python: >=3.6
License-File: LICENSE.txt
Requires-Dist: numpy
Requires-Dist: scikit-learn
